{"status":"ready","originalFilePath":"videos/project-pages.mp4","provider":"vercel-blob","providerMetadata":{"vercel-blob":{"key":"videos/project-pages.mp4","url":"https://rwvej77wzlgw9uvu.public.blob.vercel-storage.com/videos/project-pages-SnqBhpURoLKlbKoOqeT2m5GgB1L5Lk.mp4","contentType":"video/mp4"}},"createdAt":1743878220871,"updatedAt":1743878224741,"size":1518560,"sources":[{"src":"https://rwvej77wzlgw9uvu.public.blob.vercel-storage.com/videos/project-pages-SnqBhpURoLKlbKoOqeT2m5GgB1L5Lk.mp4","type":"video/mp4"}]}